dbt_docstring/__init__.py
dbt_docstring-0.1.6.dist-info/AUTHORS.md
dbt_docstring-0.1.6.dist-info/LICENSE
dbt_docstring-0.1.6.dist-info/METADATA
dbt_docstring-0.1.6.dist-info/WHEEL
dbt_docstring-0.1.6.dist-info/entry_points.txt
dbt_docstring-0.1.6.dist-info/top_level.txt
dbt_docstring-0.1.6.dist-info/RECORD
