Metadata-Version: 2.1
Name: dbt-docstring
Version: 0.1.6
Summary: Docstring dbt test & documentation in SQL file
Home-page: https://github.com/anelendata/dbt_docstring
Author: Daigo Tanaka, Anelen Co., LLC
License: UNKNOWN
Platform: UNKNOWN
Classifier: Development Status :: 4 - Beta
Classifier: License :: OSI Approved :: Apache Software License
Classifier: Operating System :: MacOS :: MacOS X
Classifier: Operating System :: POSIX :: Linux
Classifier: Programming Language :: Python :: 3.9
Classifier: Programming Language :: Python :: 3.10
Classifier: Programming Language :: Python :: 3.11
Classifier: Programming Language :: Python :: 3.12
Classifier: Programming Language :: Python :: 3.13
License-File: LICENSE
License-File: AUTHORS.md
Requires-Dist: pyyaml >=5.1
Requires-Dist: setuptools >=40.3.0
